breath/__init__.py
breath/__main__.py
breath/db.py
breath/main.py
breath/data/settings/logger.dev.json
breath/data/sounds/higher.wav
breath/data/sounds/lower.wav
breath/models/__init__.py
breath/models/base.py
breath/models/event.py
breath/models/session.py
breath/services/__init__.py
breath/services/audio.py
breath/services/pyxhookAPI.py
breath/settings/__init__.py
breath/settings/logger.py
breath/utils/__init__.py
breath/utils/path.py
breath-0.9.dist-info/METADATA
breath-0.9.dist-info/RECORD
breath-0.9.dist-info/WHEEL
breath-0.9.dist-info/entry_points.txt
breath-0.9.dist-info/top_level.txt
